turberfield_utils-0.47.0-py3.9-nspkg.pth
turberfield/utils/__init__.py
turberfield/utils/assembly.py
turberfield/utils/db.py
turberfield/utils/encoder.py
turberfield/utils/expert.py
turberfield/utils/homogeneous.py
turberfield/utils/logger.py
turberfield/utils/misc.py
turberfield/utils/orders.py
turberfield/utils/pipes.py
turberfield/utils/travel.py
turberfield/utils/doc/assembly.rst
turberfield/utils/doc/expert.rst
turberfield/utils/doc/homogeneous.rst
turberfield/utils/doc/index.rst
turberfield/utils/doc/logger.rst
turberfield/utils/doc/pipes.rst
turberfield/utils/doc/travel.rst
turberfield/utils/doc/html/assembly.html
turberfield/utils/doc/html/expert.html
turberfield/utils/doc/html/genindex.html
turberfield/utils/doc/html/homogeneous.html
turberfield/utils/doc/html/index.html
turberfield/utils/doc/html/logger.html
turberfield/utils/doc/html/pipes.html
turberfield/utils/doc/html/py-modindex.html
turberfield/utils/doc/html/search.html
turberfield/utils/doc/html/searchindex.js
turberfield/utils/doc/html/travel.html
turberfield/utils/doc/html/_sources/assembly.rst.txt
turberfield/utils/doc/html/_sources/expert.rst.txt
turberfield/utils/doc/html/_sources/homogeneous.rst.txt
turberfield/utils/doc/html/_sources/index.rst.txt
turberfield/utils/doc/html/_sources/logger.rst.txt
turberfield/utils/doc/html/_sources/pipes.rst.txt
turberfield/utils/doc/html/_sources/travel.rst.txt
turberfield/utils/doc/html/_static/alert_info_32.png
turberfield/utils/doc/html/_static/alert_warning_32.png
turberfield/utils/doc/html/_static/basic.css
turberfield/utils/doc/html/_static/bg-page.png
turberfield/utils/doc/html/_static/bullet_orange.png
turberfield/utils/doc/html/_static/doctools.js
turberfield/utils/doc/html/_static/documentation_options.js
turberfield/utils/doc/html/_static/file.png
turberfield/utils/doc/html/_static/haiku.css
turberfield/utils/doc/html/_static/jquery-3.5.1.js
turberfield/utils/doc/html/_static/jquery.js
turberfield/utils/doc/html/_static/language_data.js
turberfield_utils-0.47.0.dist-info/COPYING
turberfield_utils-0.47.0.dist-info/METADATA
turberfield_utils-0.47.0.dist-info/WHEEL
turberfield_utils-0.47.0.dist-info/entry_points.txt
turberfield_utils-0.47.0.dist-info/namespace_packages.txt
turberfield_utils-0.47.0.dist-info/top_level.txt
turberfield_utils-0.47.0.dist-info/RECORD
