Metadata-Version: 2.1
Name: turberfield-utils
Version: 0.47.0
Summary: Reusable modules from the Turberfield project.
Home-page: https://www.assembla.com/spaces/turberfield/messages
Author: D Haynes
Author-email: tundish@thuswise.org
Classifier: Operating System :: POSIX
Classifier: Programming Language :: Python :: 3.4
Classifier: License :: OSI Approved :: GNU General Public License v3 or later (GPLv3+)
License-File: COPYING
